README.rst
setup.cfg
setup.py
configr/__init__.py
configr/configr.py
configr/test.py
configr/version.py
configr.egg-info/PKG-INFO
configr.egg-info/SOURCES.txt
configr.egg-info/dependency_links.txt
configr.egg-info/not-zip-safe
configr.egg-info/requires.txt
configr.egg-info/top_level.txt
configr/../LICENSE
configr/../README.rst