Metadata-Version: 1.1
Name: configr
Version: 2018.1422.1940
Summary: configr: A practical configuration library for your Python apps.
Home-page: http://github.com/ArneBachmann/configr
Author: Arne Bachmann
Author-email: ArneBachmann@users.noreply.github.com
License: MIT
Keywords: application configuration management settings presets
Platform: UNKNOWN
Classifier: Development Status :: 5 - Production/Stable
Classifier: Intended Audience :: Developers
Classifier: License :: OSI Approved :: MIT License
Classifier: Operating System :: OS Independent
Classifier: Programming Language :: Python :: 2
Classifier: Programming Language :: Python :: 2.7
Classifier: Programming Language :: Python :: 3
Classifier: Programming Language :: Python :: 3.3
Classifier: Programming Language :: Python :: 3.4
Classifier: Programming Language :: Python :: 3.5
Classifier: Programming Language :: Python :: 3.6
Classifier: Topic :: Software Development :: Libraries :: Python Modules
